flipr_api/__init__.py
flipr_api/client.py
flipr_api/const.py
flipr_api/exceptions.py
flipr_api/session.py
flipr_api-1.6.0.dist-info/LICENSE
flipr_api-1.6.0.dist-info/WHEEL
flipr_api-1.6.0.dist-info/METADATA
flipr_api-1.6.0.dist-info/RECORD
