Metadata-Version: 2.1
Name: flipr-api
Version: 1.6.0
Summary: Python client for flipr API.
Home-page: https://github.com/cnico/flipr-api
License: GPL-3.0-or-later
Keywords: flipr,flipr-api,pool,piscine
Author: cnico
Requires-Python: >=3.10.0,<4.0.0
Classifier: Development Status :: 5 - Production/Stable
Classifier: License :: OSI Approved :: GNU General Public License v3 or later (GPLv3+)
Classifier: Operating System :: OS Independent
Classifier: Programming Language :: Python :: 3
Classifier: Programming Language :: Python :: 3.10
Requires-Dist: python-dateutil (>=2.7.0,<3.0.0)
Requires-Dist: requests (>=2.25.0,<3.0.0)
Project-URL: Changelog, https://github.com/cnico/flipr-api/releases
Project-URL: Documentation, https://flipr-api.readthedocs.io
Project-URL: Repository, https://github.com/cnico/flipr-api
